README.md
setup.py
thatool/__init__.py
thatool.egg-info/PKG-INFO
thatool.egg-info/SOURCES.txt
thatool.egg-info/dependency_links.txt
thatool.egg-info/requires.txt
thatool.egg-info/top_level.txt
thatool/colvar/SwitchFunction.py
thatool/colvar/__init__.py
thatool/colvar/cv_CoordNum.py
thatool/colvar/cv_PairANGLE.py
thatool/colvar/cv_Steinhardt.py
thatool/colvar/cv_fccCUBIC.py
thatool/colvar/cv_localCRYSTALLINITY.py
thatool/colvar/find_neighbors.py
thatool/colvar/sph_harmonics.py
thatool/colvar/voronoi_analysis.py
thatool/free_energy/Helmholtz_excess_UF.py
thatool/free_energy/__init__.py
thatool/free_energy/meltingBarrier.py
thatool/free_energy/replica_MD_average.py
thatool/free_energy/replica_SteerMD_average.py
thatool/free_energy/replica_logPD_integration.py
thatool/io/Traj_Frame.py
thatool/io/Traj_Multi_Frames.py
thatool/io/__init__.py
thatool/io/define_script.py
thatool/io/read_block.py
thatool/io/read_data.py
thatool/io/read_script.py
thatool/io/write_script.py
thatool/model/D1tube.py
thatool/model/D2haxagonal.py
thatool/model/D3crystal.py
thatool/model/__init__.py
thatool/model/box_orientation_.py
thatool/model/combining_LJ_interface.py
thatool/model/coord_convert.py
thatool/model/coord_rotation.py
thatool/model/forcefield_info.py
thatool/model/periodicBC_operation.py
thatool/model/polymer_mbuild.py
thatool/model/polymer_pysimm.py
thatool/model/shells_fcc_.py
thatool/utils/UserLMFIT.py
thatool/utils/__init__.py
thatool/utils/compute_angle.py
thatool/utils/compute_distance.py
thatool/utils/compute_tensor.py
thatool/utils/data.py
thatool/utils/detect_sign_change.py
thatool/utils/fitting.py
thatool/utils/grid_box.py
thatool/utils/intersect_point.py
thatool/utils/many_stuff.py
thatool/utils/row_operation.py
thatool/utils/string_index.py
thatool/utils/thang_plot.mplstyle
thatool/utils/unit.py
thatool/vis/__init__.py
thatool/vis/matplot_param.py
thatool/vis/matplot_style.py
thatool/vis/ovito_modifier.py
thatool/vis/mplstyle/light.mplstyle