Metadata-Version: 2.1
Name: thatool
Version: 1.1.6
Summary: Python package
Author: thangckt
Author-email: thangckt@gmail.com
License: MIT
Classifier: Development Status :: 3 - Alpha
Classifier: Topic :: Software Development
Classifier: Programming Language :: Python :: 3.7
Requires-Python: >=3.6
